src/__init__.py
src/aiml/__init__.py
src/daqs/__init__.py
src/demo/__init__.py
src/prep/__init__.py
src/unst/__init__.py
src/util/__init__.py
EgC_Demo_Package-0.0.17.dist-info/METADATA
EgC_Demo_Package-0.0.17.dist-info/WHEEL
EgC_Demo_Package-0.0.17.dist-info/license
EgC_Demo_Package-0.0.17.dist-info/top_level.txt
EgC_Demo_Package-0.0.17.dist-info/RECORD
