Metadata-Version: 2.1
Name: EgC-Demo-Package
Version: 0.0.17
Summary: A small example package from EGC
Home-page: https://github.com/EgC-Team/EngineeringGoesCloud
Author: liu1stu
Author-email: weihan.liu1994@hotmail.com
License: UNKNOWN
Platform: UNKNOWN
Classifier: Programming Language :: Python :: 3
Classifier: License :: OSI Approved :: MIT License
Classifier: Operating System :: OS Independent
Requires-Python: >=3.7
Requires-Dist: numpy
Requires-Dist: xlrd
Provides-Extra: all
Requires-Dist: scipy ; extra == 'all'
Requires-Dist: pandas ; extra == 'all'
Requires-Dist: asammdf ; extra == 'all'
Provides-Extra: analysisdrvcyc
Requires-Dist: asammdf ; extra == 'analysisdrvcyc'
Requires-Dist: pandas ; extra == 'analysisdrvcyc'
Provides-Extra: modelingann
Requires-Dist: pandas ; extra == 'modelingann'
Requires-Dist: scipy ; extra == 'modelingann'
